mlcheck/__init__.py
mlcheck/core.py
mlcheck-0.0.1.dist-info/METADATA
mlcheck-0.0.1.dist-info/WHEEL
mlcheck-0.0.1.dist-info/top_level.txt
mlcheck-0.0.1.dist-info/RECORD
