Metadata-Version: 2.4
Name: mlcheck
Version: 0.0.1
Summary: Pre-flight validation and reliability checks for ML pipelines
Author: Amaresh Maity
License-Expression: MIT
Requires-Python: >=3.9
Requires-Dist: numpy
Requires-Dist: pandas
Provides-Extra: dev
Requires-Dist: pytest; extra == "dev"
Requires-Dist: ruff; extra == "dev"
Requires-Dist: build; extra == "dev"
Requires-Dist: twine; extra == "dev"
